{"cameraMode":{"drawMode":0,"name":"Shaded","section":"Shading Mode"},"sceneLighting":true,"audioPlay":false,"sceneViewState":{"m_AlwaysRefresh":false,"showFog":true,"showSkybox":true,"showFlares":true,"showImageEffects":true,"showParticleSystems":true,"showVisualEffectGraphs":true,"m_FxEnabled":true},"in2DMode":false,"pivot":{"x":-6.21434211730957,"y":86.78468322753906,"z":-362.7799377441406},"rotation":{"x":0.1732027381658554,"y":0.12592263519763947,"z":-0.022170865908265115,"w":0.9766405820846558},"size":11.808395385742188,"orthographic":false}